{
  "events": [


    
    {
      "name": "Smooth 1 -  Portugal vs Armenia",
      "link": "https://nirutv.online/Player/page.html?src=https://nirutv.online/Player/soco?id=327159"
    },
    
    {
      "name": "Smooth 2 -  Portugal vs Armenia",
      "link": "https://nirutv.online/VIP/ads.html"
    },

  {
      "name": "Smooth 3 -  Portugal vs Armenia",
      "link": "https://nirutv.online/Player/page.html?src=https://nirutv.online/Player/dplyrr?url=https://hls.suanzsd6.com/sd-6MtMP42NaZQ3VnrYXZ.m3u8?txSecret=b03d4b76050604c291580a21af51f417&txTime=68BDACD1"
    },
{
      "name": "HD Link 1 -  Portugal vs Armenia",
      "link": "https://nirutv.online/Player/page2.html?src=https://nirutv.online/Player/socohd?id=9912100"
    },
    
    {
      "name": "HD Link 2 -  Portugal vs Armenia",
      "link": "https://nirutv.online/VIP/ads.html"
    },
{
      "name": "HD Link 3 -  Portugal vs Armenia",
      "link": "https://nirutv.online/Player/page2.html?src=https://nirutv.online/Player/soco?id=494201"
    },

    
 {
      "name": "Full HD Link 1 -  Portugal vs Armenia",
      "link": "https://nirutv.online/VIP/ads.html"
    },

{
      "name": "Full HD Link 2 -  Portugal vs Armenia",
      "link": "https://nirutv.online/Player/page2.html?src=https://nirutv.online/Player/socohd?id=9912100"
    },
    
 {
      "name": "Full HD Link 3-  Portugal vs Armenia",
    "link": "https://nirutv.online/Player/page2.html?src=https://nirutv.online/Player/soco?id=9912103"
    
    }


  ],
  "styles": {
    "livee": "display: flex; justify-content: space-between; align-items: center; text-decoration: none; color: inherit; margin: 5px 0; padding: 5px; border: 2px solid #000; border-radius: 5px; cursor: poAC Milanr; transition: box-shadow 0.3s ease; background-color: red; color: white;",
    "liveeHover": "box-shadow: 0 4px 8px rgba(0, 0, 0, 0.2);",
    "liveeName": "flex: 2; text-align: center; color: white; font-weight: bold;"
  }
}
